pycountsiris0614/__init__.py
pycountsiris0614/plotting.py
pycountsiris0614/pycounts.py
pycountsiris0614-0.1.1.dist-info/LICENSE
pycountsiris0614-0.1.1.dist-info/WHEEL
pycountsiris0614-0.1.1.dist-info/METADATA
pycountsiris0614-0.1.1.dist-info/RECORD
