Metadata-Version: 2.1
Name: pycountsiris0614
Version: 0.1.1
Summary: Calculate word counts in a text file!
License: MIT
Author: iris
Requires-Python: >=3.9
Classifier: License :: OSI Approved :: MIT License
Classifier: Programming Language :: Python :: 3
Classifier: Programming Language :: Python :: 3.9
Classifier: Programming Language :: Python :: 3.10
Requires-Dist: matplotlib (>=3.8.2)
